csr_utils/__init__.py
csr_utils/csr_utils.py
csr_utils-0.1.3.dist-info/METADATA
csr_utils-0.1.3.dist-info/RECORD
csr_utils-0.1.3.dist-info/WHEEL
csr_utils-0.1.3.dist-info/top_level.txt
tests/__init__.py
tests/test_csr_utils.py
