Metadata-Version: 2.1
Name: csr-utils
Version: 0.1.3
Summary: Utility functions for scalable handling of CSR matrices
Home-page: https://github.com/narges-rzv/csr_utils
Author: Narges Razavian
Author-email: nsr3@nyu.edu
License: UNKNOWN
Platform: UNKNOWN
Classifier: Programming Language :: Python :: 3
Classifier: License :: OSI Approved :: MIT License
Classifier: Operating System :: OS Independent
Requires-Dist: scipy
Requires-Dist: numpy
